ergast_py/__init__.py
ergast_py/constants/__init__.py
ergast_py/constants/expected.py
ergast_py/constants/status_type.py
ergast_py/ergast.py
ergast_py/helpers.py
ergast_py/models/__init__.py
ergast_py/models/average_speed.py
ergast_py/models/circuit.py
ergast_py/models/constructor.py
ergast_py/models/constructor_standing.py
ergast_py/models/driver.py
ergast_py/models/driver_standing.py
ergast_py/models/fastest_lap.py
ergast_py/models/lap.py
ergast_py/models/location.py
ergast_py/models/pit_stop.py
ergast_py/models/race.py
ergast_py/models/result.py
ergast_py/models/season.py
ergast_py/models/standings_list.py
ergast_py/models/status.py
ergast_py/models/timing.py
ergast_py/requester.py
ergast_py/type_constructor.py
ergast_py-0.7.0.dist-info/LICENSE.md
ergast_py-0.7.0.dist-info/WHEEL
ergast_py-0.7.0.dist-info/METADATA
ergast_py-0.7.0.dist-info/RECORD
