Metadata-Version: 2.1
Name: ergast-py
Version: 0.7.0
Summary: A comprehensive Python wrapper for the Ergast API.
Home-page: https://github.com/Samuel-Roach/ergast-py
License: GPL-3.0-only
Author: Samuel Roach
Author-email: samuelroach.2000@gmail.com
Requires-Python: >=3.9,<4.0
Classifier: License :: OSI Approved :: GNU General Public License v3 (GPLv3)
Classifier: Programming Language :: Python :: 3
Classifier: Programming Language :: Python :: 3.9
Classifier: Programming Language :: Python :: 3.10
Classifier: Programming Language :: Python :: 3.11
Requires-Dist: requests (>=2.27.1,<3.0.0)
Requires-Dist: uritemplate (>=4.1.1,<5.0.0)
Project-URL: Repository, https://github.com/Samuel-Roach/ergast-py
